{"100":"Skelic","101":"Zaleo","102":"Joltooth","103":"Dobo","104":"Infernix","105":"Kyogo","106":"Dorogo","107":"Wiledile","108":"Mawamurk","109":"Ampole","110":"Amphiton","111":"Meditoad","112":"Pwuff","113":"Bloatox","114":"Barblast","115":"Swimp","116":"Snapr","117":"Garlash","118":"Hydrini","119":"Bezeldew","120":"Deludrix","121":"Ceratot","122":"Trepodon","123":"Colossotrops","124":"Cupoink","125":"Hoganosh","126":"Mochibi","127":"Totemochi","128":"Mocho","129":"Gwurm","130":"Odasho","131":"Spreezy","132":"Pipsee","133":"Dandylil","134":"Whippledriff","135":"Vari","136":"Cervolen","137":"Wendolen","138":"Kirolen","139":"Zepholen","140":"Venolen","141":"Wresolen","142":"Buzzolen","143":"Tundrolen","144":"Pyrolen","145":"Hydrolen","153":"Copling","154":"Copperage","155":"Oxidrake","156":"Spirivii","157":"Eidohusk","158":"Harvesect","159":"Snowl","160":"Stricicle","161":"Wintrix","162":"Snagull","163":"Snagulp","164":"Snagoop","165":"Makame","166":"Makoro","167":"Tsukame","168":"Cavenish","169":"Banfino","170":"Kanki","171":"Kanibo","172":"Sharpod","173":"Samarine","174":"Lumica","175":"Lumello","176":"Polypi","177":"Laphyra","178":"Jellusa","179":"Taoshi","180":"Taoshinu","181":"Kittone","182":"Lyricat","183":"Boonary","184":"Somata","185":"Clionae","186":"Cinnaboo","187":"Cinnogre","188":"Swirelle","189":"Swishy","190":"Fiscarna","191":"Bunpuff","192":"Bunnecki","193":"Dractus","194":"Frutress","195":"Seedrake","196":"Volpup","197":"Halvantic","198":"Impkin","199":"Grimmick","200":"Imperior","201":"Mistlebud","202":"Hollibunch","203":"Cryocub","204":"Barbadger","205":"Kyeggo","206":"Doreggo","207":"Dreggodyne","208":"Wispur","209":"Lampurge","210":"Charonyx","211":"Smoal","212":"Charkiln","213":"Billoforge","214":"Sherbot","215":"Llamba","216":"Choochew","217":"Loomala","218":"Fentern","219":"Weaselin","220":"Singeel","221":"Moreel","222":"Crabushi","223":"Crabtana","224":"Teripod","225":"Teridescent","226":"Skampi","227":"Prawnsu","228":"Shrimposte","229":"Dokan","230":"Dokumori","231":"Mirrami","232":"Mirraith","233":"Thawmin","234":"Leshent","241":"Duskit","242":"Ikazune","243":"Protogon","244":"Dakuda","247":"Mutagon","248":"Cephalops","249":"Elephage","250":"Phagenaut","251":"Arceros","252":"Glacadia","253":"Novadeaus","259":"Metronette","260":"Wabalisc","261":"Nymaurae","262":"Cosmiore","263":"Nevermare","264":"Akhalos","265":"Gargolem","266":"Celesting","267":"Odoyaga","001":"Embit","002":"Rabburn","003":"Searknight","004":"Dripple","005":"Reptide","006":"Luminami","007":"Fevine","008":"Felver","009":"Tahtab","010":"Eaglit","011":"Torprey","012":"Falkyrie","013":"Vambat","014":"Dimpire","015":"Vesperatu","016":"Snocub","017":"Snowki","018":"Himbrr","019":"Weevolt","020":"Stozap","021":"Zuelong","022":"Twilat","023":"Umbrat","024":"Luxoar","025":"Tiklipse","026":"Cathorn","027":"Propae","028":"Cynamoth","029":"Sumobito","030":"Twittle","031":"Paratweet","032":"Avitross","033":"Pyder","034":"Swolder","035":"Antsee","036":"Florant","037":"Grubby","038":"Coonucopia","039":"Terrafly","040":"Terraclaw","041":"Kleptyke","042":"Ragoon","043":"Babore","044":"Boarrok","045":"Geklow","046":"Eleguana","047":"Slugling","048":"Escargrow","049":"Gastroak","050":"Kabunga","051":"Wiki-Wiki","052":"Chartiki","053":"Waka-Laka","054":"Shawchi","055":"Rakrawla","056":"Sedimars","057":"Gumpod","058":"Ventacean","059":"Phancub","060":"Ursoul","061":"Ursnac","062":"Whispup","063":"Revenine","064":"Skilava","065":"Geksplode","066":"Eruptidon","067":"Craytal","068":"Krakaloa","069":"Volkaloa","070":"Festifir","071":"Igneol","072":"Chrysite","073":"Obsidrugon","074":"Cafnote","075":"Trumbull","076":"Mootune","077":"Gobbidemic","078":"Icigool","079":"Pyramind","080":"Pharoglyph","081":"Burroach","082":"Garbantis","083":"Whimpor","084":"Stratusoar","085":"Territi","086":"Dyeborg","087":"Operaptor","088":"Concredon","089":"Tyrecks","090":"Chompactor","091":"Munchweel","092":"Scorb","093":"Veylens","094":"Gardrone","095":"Poochrol","096":"Hunder","097":"Goppie","098":"Arapaigo","099":"Pyke"}